tutor_k8s_harmony_plugin/__about__.py
tutor_k8s_harmony_plugin/__init__.py
tutor_k8s_harmony_plugin/commands.py
tutor_k8s_harmony_plugin/plugin.py
tutor_k8s_harmony_plugin/harmony_search/__init__.py
tutor_k8s_harmony_plugin/harmony_search/base.py
tutor_k8s_harmony_plugin/harmony_search/elasticsearch.py
tutor_k8s_harmony_plugin/harmony_search/opensearch.py
tutor_k8s_harmony_plugin/patches/discovery-common-settings
tutor_k8s_harmony_plugin/patches/k8s-services
tutor_k8s_harmony_plugin/patches/kustomization
tutor_k8s_harmony_plugin/patches/openedx-common-settings
tutor_k8s_harmony_plugin/templates/k8s_harmony/k8s/deployment-revision-history.yaml
tutor_k8s_harmony_plugin/templates/k8s_harmony/k8s/shared-search-cert-patch-volumeless.yaml
tutor_k8s_harmony_plugin/templates/k8s_harmony/k8s/shared-search-cert-patch.yaml
tutor_contrib_harmony-18.0.1.dist-info/METADATA
tutor_contrib_harmony-18.0.1.dist-info/WHEEL
tutor_contrib_harmony-18.0.1.dist-info/entry_points.txt
tutor_contrib_harmony-18.0.1.dist-info/top_level.txt
tutor_contrib_harmony-18.0.1.dist-info/RECORD
